auto_diffusers/__init__.py
auto_diffusers/pipeline_easy.py
auto_diffusers/py.typed
auto_diffusers-2.0.36.dist-info/licenses/LICENSE
auto_diffusers-2.0.36.dist-info/METADATA
auto_diffusers-2.0.36.dist-info/WHEEL
auto_diffusers-2.0.36.dist-info/top_level.txt
auto_diffusers-2.0.36.dist-info/RECORD
