Metadata-Version: 2.4
Name: auto_diffusers
Version: 2.0.36
Summary: diffusers with search engine
Home-page: https://github.com/suzukimain/auto_diffusers
Author: suzukimain
Author-email: gt13579552@gmail.com
License: Apache 2.0 License
Keywords: huggingface civitai diffusers model search deep learning diffusion pytorch stable diffusion
Classifier: Development Status :: 5 - Production/Stable
Classifier: Intended Audience :: Developers
Classifier: Intended Audience :: Education
Classifier: Intended Audience :: Science/Research
Classifier: License :: OSI Approved :: Apache Software License
Classifier: Topic :: Scientific/Engineering :: Artificial Intelligence
Classifier: Programming Language :: Python :: 3
Classifier: Programming Language :: Python :: 3.8
Classifier: Programming Language :: Python :: 3.9
Classifier: Programming Language :: Python :: 3.10
Classifier: Programming Language :: Python :: 3.11
Requires-Python: >=3.8.0
License-File: LICENSE
Requires-Dist: diffusers>=0.36.0
Requires-Dist: transformers>=4.57.3
Dynamic: author
Dynamic: author-email
Dynamic: classifier
Dynamic: description
Dynamic: description-content-type
Dynamic: home-page
Dynamic: keywords
Dynamic: license
Dynamic: license-file
Dynamic: requires-dist
Dynamic: requires-python
Dynamic: summary
